{
  "full_name": "Ethan Corey",
  "email": "ethanscorey@gmail.com",
  "github_username": "ethanscorey",
  "project_name": "Python Boilerplate",
  "project_slug": "{{ cookiecutter.project_name.lower().replace(' ', '_').replace('-', '_') }}",
  "project_short_description": "Python Boilerplate contains all the boilerplate you need to create a Python package.",
  "python_version": "3.10",
  "pypi_username": "{{ cookiecutter.github_username }}",
  "version": "0.1.0",
  "mypy": "y",
  "open_source_license": ["MIT license", "BSD license", "ISC license", "Apache Software License 2.0", "GNU General Public License v3", "Not open source"]
}
